spatbox/__init__.py
spatbox/corrdinate.py
spatbox/geocode.py
spatbox/datasets/__init__.py
spatbox/datasets/china.zip
spatbox/datasets/china_city_pcs.zip
spatbox/datasets/lp.zip
spatbox/datasets/mws.zip
spatbox/datasets/nineline.zip
spatbox/datasets/xian.zip
spatbox/model/__init__.py
spatbox/model/gwann.py
spatbox/model/srgcnn.py
spatbox/plot/__init__.py
spatbox/plot/colormaps.py
spatbox/raster/__init__.py
spatbox/raster/convert.py
spatbox/raster/mask.py
spatbox/raster/reproject.py
spatbox/raster/resample.py
spatbox/vector/__init__.py
spatbox/vector/grid.py
spatbox-0.1.7.dist-info/METADATA
spatbox-0.1.7.dist-info/WHEEL
spatbox-0.1.7.dist-info/top_level.txt
spatbox-0.1.7.dist-info/RECORD
