Metadata-Version: 2.1
Name: spatbox
Version: 0.1.7
Summary: A Python Library For GeoSpatial Data Proressing And Modeling
Home-page: https://github.com/SpatLyu/SpatBox
Author: SpatLyu
Author-email: 3180929657@qq.com
License: MIT license
